ai_code_forge_deprecated/__init__.py
ai_code_forge_deprecated/__main__.py
ai_code_forge_deprecated/main.py
ai_code_forge-3.0.0.dist-info/METADATA
ai_code_forge-3.0.0.dist-info/WHEEL
ai_code_forge-3.0.0.dist-info/entry_points.txt
ai_code_forge-3.0.0.dist-info/RECORD
