Metadata-Version: 2.4
Name: ai-code-forge
Version: 3.0.0
Summary: DEPRECATED: This package has been renamed to 'acforge'. Please use 'uv tool install acforge' instead.
Project-URL: Homepage, https://github.com/ondrasek/ai-code-forge
Project-URL: Repository, https://github.com/ondrasek/ai-code-forge
Project-URL: Issues, https://github.com/ondrasek/ai-code-forge/issues
Project-URL: New Package, https://pypi.org/project/acforge/
Author-email: AI Code Forge <noreply@example.com>
License: MIT
Keywords: acforge,ai,cli,configuration,deprecated,development,templates
Classifier: Development Status :: 7 - Inactive
Classifier: Intended Audience :: Developers
Classifier: License :: OSI Approved :: MIT License
Classifier: Programming Language :: Python :: 3
Classifier: Programming Language :: Python :: 3.9
Classifier: Programming Language :: Python :: 3.10
Classifier: Programming Language :: Python :: 3.11
Classifier: Programming Language :: Python :: 3.12
Classifier: Programming Language :: Python :: 3.13
Classifier: Topic :: Software Development
Requires-Python: >=3.9
